bdscore/__init__.py
bdscore/enums.py
bdscore/result.py
bdscore/validator.py
bdscore/services/__init__.py
bdscore/services/common.py
bdscore/services/dataflex.py
bdscore/services/datamanagement.py
bdscore/services/datapack.py
bdscore/services/utils.py
bdscore-0.1.0b29.dist-info/METADATA
bdscore-0.1.0b29.dist-info/WHEEL
bdscore-0.1.0b29.dist-info/top_level.txt
bdscore-0.1.0b29.dist-info/RECORD
