Metadata-Version: 2.4
Name: bdscore
Version: 0.1.0b29
Summary: Biblioteca oficial da BDS DataSolution para integração com dados de mercado e dados proprietários.
Author-email: BDS DataSolution <comercial@bdsdatasolution.com.br>
Keywords: SaaS,Finance,MarketData,MarketRisk,BigData,Analytics,API,DataSolution,BDS,FinancialData,RiskManagement,Integration,DataScience,Quantitative,Trading,Investments,PaaS,BDaaS,ArtificialIntelligence,MachineLearning,OpenFinance,Fintech,DataHub
Requires-Python: >=3.9
Requires-Dist: requests
Requires-Dist: pandas
Requires-Dist: xlsxwriter
Requires-Dist: numpy
Requires-Dist: tomli
Provides-Extra: dev
Requires-Dist: pytest; extra == "dev"
Requires-Dist: pytest-dotenv; extra == "dev"
